lemminflect/__init__.py
lemminflect/config.py
lemminflect/codecs/FormsTable.py
lemminflect/codecs/InflTCorpFileCodec.py
lemminflect/codecs/InflectionLUCodec.py
lemminflect/codecs/LemmaLUCodec.py
lemminflect/codecs/LemmaTCorpFileCodec.py
lemminflect/codecs/OverridesCodec.py
lemminflect/codecs/__init__.py
lemminflect/core/InflectionRules.py
lemminflect/core/Inflections.py
lemminflect/core/Lemmatizer.py
lemminflect/core/LemmatizerRules.py
lemminflect/core/LexicalUtils.py
lemminflect/core/__init__.py
lemminflect/kmodels/KInfer.py
lemminflect/kmodels/KerasModel.py
lemminflect/kmodels/ModelInfl.py
lemminflect/kmodels/ModelInflInData.py
lemminflect/kmodels/ModelLemma.py
lemminflect/kmodels/ModelLemmaClasses.py
lemminflect/kmodels/ModelLemmaInData.py
lemminflect/kmodels/__init__.py
lemminflect/resources/infl_lu.csv.gz
lemminflect/resources/infl_overrides.csv
lemminflect/resources/lemma_lu.csv.gz
lemminflect/resources/lemma_overrides.csv
lemminflect/resources/model_infl.pkl.gz
lemminflect/resources/model_lemma.pkl.gz
lemminflect/slexicon/SKey.py
lemminflect/slexicon/SPECIALISTEntry.py
lemminflect/slexicon/SPECIALISTExtractor.py
lemminflect/slexicon/__init__.py
lemminflect/utils/CorpusUtils.py
lemminflect/utils/DataContainer.py
lemminflect/utils/ProgressBar.py
lemminflect/utils/Singleton.py
lemminflect/utils/Unigrams.py
lemminflect/utils/__init__.py
lemminflect-0.2.2.dist-info/LICENSE
lemminflect-0.2.2.dist-info/METADATA
lemminflect-0.2.2.dist-info/WHEEL
lemminflect-0.2.2.dist-info/top_level.txt
lemminflect-0.2.2.dist-info/RECORD
