Metadata-Version: 2.1
Name: lemminflect
Version: 0.2.2
Summary: A python module for English lemmatization and inflection.
Home-page: https://github.com/bjascob/LemmInflect
Author: Brad Jascob
Author-email: bjascob@msn.com
License: UNKNOWN
Platform: UNKNOWN
Classifier: Programming Language :: Python :: 3
Classifier: License :: OSI Approved :: MIT License
Classifier: Operating System :: OS Independent
